README.md
setup.py
aionlinelab1.egg-info/PKG-INFO
aionlinelab1.egg-info/SOURCES.txt
aionlinelab1.egg-info/dependency_links.txt
aionlinelab1.egg-info/entry_points.txt
aionlinelab1.egg-info/requires.txt
aionlinelab1.egg-info/top_level.txt
src/__init__.py
src/logic.py
src/main.py